voltage/__init__.py
voltage/asset.py
voltage/categories.py
voltage/channels.py
voltage/client.py
voltage/embed.py
voltage/enums.py
voltage/errors.py
voltage/file.py
voltage/flag.py
voltage/invites.py
voltage/member.py
voltage/message.py
voltage/messageable.py
voltage/notsuplied.py
voltage/notsupplied.py
voltage/permissions.py
voltage/roles.py
voltage/server.py
voltage/user.py
voltage/utils.py
voltage/ext/commands/__init__.py
voltage/ext/commands/check.py
voltage/ext/commands/client.py
voltage/ext/commands/cog.py
voltage/ext/commands/command.py
voltage/ext/commands/converters.py
voltage/ext/commands/help.py
voltage/internals/__init__.py
voltage/internals/cache.py
voltage/internals/http.py
voltage/internals/ws.py
voltage/types/__init__.py
voltage/types/channel.py
voltage/types/embed.py
voltage/types/file.py
voltage/types/http.py
voltage/types/message.py
voltage/types/server.py
voltage/types/user.py
voltage/types/ws.py
voltage/utils/__init__.py
voltage/utils/eval.py
voltage-0.1.5a8.dist-info/LICENSE
voltage-0.1.5a8.dist-info/METADATA
voltage-0.1.5a8.dist-info/WHEEL
voltage-0.1.5a8.dist-info/top_level.txt
voltage-0.1.5a8.dist-info/RECORD
