Metadata-Version: 2.1
Name: voltage
Version: 0.1.5a8
Summary: A Simple Pythonic Asynchronous API wrapper for Revolt.
Home-page: https://github.com/EnokiUN/voltage
Author: EnokiUN
License: MIT
Project-URL: Documentation, https://revolt-voltage.readthedocs.io/en/latest
Project-URL: Issue tracker, https://github.com/enokiun/voltage/issues
Platform: UNKNOWN
Classifier: Development Status :: 5 - Production/Stable
Classifier: License :: OSI Approved :: MIT License
Classifier: Intended Audience :: Developers
Classifier: Natural Language :: English
Classifier: Operating System :: OS Independent
Classifier: Programming Language :: Python :: 3.8
Classifier: Programming Language :: Python :: 3.9
Classifier: Programming Language :: Python :: 3.10
Classifier: Programming Language :: Python :: 3.11
Classifier: Topic :: Internet
Classifier: Topic :: Software Development :: Libraries
Classifier: Topic :: Utilities
Requires-Python: >=3.8.0
License-File: LICENSE
Requires-Dist: aiohttp
Requires-Dist: typing-extensions
Requires-Dist: py-ulid
